HL7000/__init__.py
HL7000/__main__.py
HL7000/helper_functions.py
HL7000/HL7000.py
hl7000-0.1.0.dist-info/WHEEL
hl7000-0.1.0.dist-info/METADATA
hl7000-0.1.0.dist-info/RECORD
