Metadata-Version: 2.1
Name: hl7000
Version: 0.1.0
Summary: Processing toolkit for Seba HL7000
License: MIT
Author: Cody Scott
Author-email: jcodyscott@gmail.com
Requires-Python: >=3.6,<4.0
Classifier: License :: OSI Approved :: MIT License
Classifier: Programming Language :: Python :: 3
Classifier: Programming Language :: Python :: 3.10
Classifier: Programming Language :: Python :: 3.6
Classifier: Programming Language :: Python :: 3.7
Classifier: Programming Language :: Python :: 3.8
Classifier: Programming Language :: Python :: 3.9
Requires-Dist: pandas (>=1.4.1,<2.0.0)
